models/KNN.py
models/linear.py
models/trees.py
preprocessing/data_split.py
preprocessing/encoders.py
preprocessing/scaling.py
sikhana-0.1.1.dist-info/METADATA
sikhana-0.1.1.dist-info/WHEEL
sikhana-0.1.1.dist-info/top_level.txt
sikhana-0.1.1.dist-info/RECORD
