Metadata-Version: 2.4
Name: sikhana
Version: 0.1.1
Summary: A very robust machine learning library
Author-email: jatin <jcooldiscord66@gmail.com>
License: MIT
Requires-Python: >=3.8
Requires-Dist: numpy>=1.24
